programgarden_community/__init__.py
programgarden_community/overseas_futureoption/cancel_order_conditions/price_range_canceller/__init__.py
programgarden_community/overseas_futureoption/modify_order_conditions/tracking_price/__init__.py
programgarden_community/overseas_futureoption/new_order_conditions/future_split_funds/__init__.py
programgarden_community/overseas_futureoption/new_order_conditions/loss_cut/__init__.py
programgarden_community/overseas_futureoption/strategy_conditions/ad/__init__.py
programgarden_community/overseas_futureoption/strategy_conditions/adx/__init__.py
programgarden_community/overseas_futureoption/strategy_conditions/atr/__init__.py
programgarden_community/overseas_futureoption/strategy_conditions/beta/__init__.py
programgarden_community/overseas_futureoption/strategy_conditions/bollinger_bands/__init__.py
programgarden_community/overseas_futureoption/strategy_conditions/candle_patterns/__init__.py
programgarden_community/overseas_futureoption/strategy_conditions/cci/__init__.py
programgarden_community/overseas_futureoption/strategy_conditions/ema_risk_adjusted_trend/__init__.py
programgarden_community/overseas_futureoption/strategy_conditions/kama/__init__.py
programgarden_community/overseas_futureoption/strategy_conditions/macd_momentum_shift/__init__.py
programgarden_community/overseas_futureoption/strategy_conditions/obv/__init__.py
programgarden_community/overseas_futureoption/strategy_conditions/parabolic_sar/__init__.py
programgarden_community/overseas_futureoption/strategy_conditions/rsi_stochastic_oscillator/__init__.py
programgarden_community/overseas_futureoption/strategy_conditions/sma_ema_trend_cross/__init__.py
programgarden_community/overseas_futureoption/strategy_conditions/williams_r/__init__.py
programgarden_community/overseas_stock/cancel_order_conditions/price_range_canceller/__init__.py
programgarden_community/overseas_stock/cancel_order_conditions/turtle_safety_cancel/__init__.py
programgarden_community-0.1.15.dist-info/METADATA
programgarden_community-0.1.15.dist-info/WHEEL
programgarden_community-0.1.15.dist-info/RECORD
