Metadata-Version: 2.3
Name: programgarden-community
Version: 0.1.15
Summary: 증권 분석에 필요한 외부 전략 모아둔 플러그인
Author: 프로그램동산
Author-email: coding@programgarden.com
Requires-Python: >=3.10
Classifier: Programming Language :: Python :: 3
Classifier: Programming Language :: Python :: 3.10
Classifier: Programming Language :: Python :: 3.11
Classifier: Programming Language :: Python :: 3.12
Classifier: Programming Language :: Python :: 3.13
Requires-Dist: bs4 (>=0.0.2,<0.0.3)
Requires-Dist: croniter (>=6.0.0,<7.0.0)
Requires-Dist: programgarden-core (>=0.1.12,<0.2.0)
Requires-Dist: programgarden-finance (>=0.1.13,<0.2.0)
Requires-Dist: pydantic (>=2.11.7,<3.0.0)
Requires-Dist: python-dotenv (>=1.1.1,<2.0.0)
